cvat_sdk_i_digit-0.0.9.dist-info/METADATA
cvat_sdk_i_digit-0.0.9.dist-info/WHEEL
cvat_sdk_i_digit-0.0.9.dist-info/entry_points.txt
cvat_sdk_i_digit-0.0.9.dist-info/licenses/LICENSE
cvat_sdk_i_digit/__init__.py
cvat_sdk_i_digit/config.py
cvat_sdk_i_digit/cvat_api.py
cvat_sdk_i_digit-0.0.9.dist-info/RECORD
